pytest_zy/__init__.py
pytest_zy/plugin.py
pytest_zy/common/HttpRequest.py
pytest_zy/common/ReportNotify.py
pytest_zy/common/Runner.py
pytest_zy/common/__init__.py
pytest_zy/common/allure_step_validate.py
pytest_zy/common/create_function.py
pytest_zy/common/db.py
pytest_zy/common/exceptions.py
pytest_zy/common/extract.py
pytest_zy/common/log.py
pytest_zy/common/my_builtins.py
pytest_zy/common/render_template_obj.py
pytest_zy/common/run_yaml.py
pytest_zy/common/validate.py
pytest_zy-1.2.0.dist-info/LICENSE
pytest_zy-1.2.0.dist-info/METADATA
pytest_zy-1.2.0.dist-info/WHEEL
pytest_zy-1.2.0.dist-info/entry_points.txt
pytest_zy-1.2.0.dist-info/top_level.txt
pytest_zy-1.2.0.dist-info/RECORD
