Metadata-Version: 2.1
Name: pytest-zy
Version: 1.2.0
Summary: 接口自动化测试框架
Author-email: 浪浪 <zy1834529768@gmail.com>
License: Apache License
Classifier: Programming Language :: Python :: 3
Classifier: License :: OSI Approved :: MIT License
Classifier: Operating System :: OS Independent
Requires-Python: >=3.10
License-File: LICENSE
Requires-Dist: allure-pytest ==2.13.3
Requires-Dist: allure-python-commons ==2.13.3
Requires-Dist: asttokens ==2.4.1
Requires-Dist: attrs ==23.2.0
Requires-Dist: backcall ==0.2.0
Requires-Dist: beautifulsoup4 ==4.12.3
Requires-Dist: black ==24.2.0
Requires-Dist: bleach ==6.1.0
Requires-Dist: certifi ==2024.2.2
Requires-Dist: charset-normalizer ==2.1.1
Requires-Dist: click ==8.1.7
Requires-Dist: colorama ==0.4.6
Requires-Dist: decorator ==5.1.1
Requires-Dist: defusedxml ==0.7.1
Requires-Dist: DingtalkChatbot ==1.5.7
Requires-Dist: docopt ==0.6.2
Requires-Dist: executing ==2.0.1
Requires-Dist: Faker ~=15.3.4
Requires-Dist: fastjsonschema ==2.19.1
Requires-Dist: greenlet ==3.0.3
Requires-Dist: idna ==3.6
Requires-Dist: iniconfig ==2.0.0
Requires-Dist: ipython ==8.12.3
Requires-Dist: jedi ==0.19.1
Requires-Dist: Jinja2 ~=3.1.2
Requires-Dist: jmespath ==1.0.1
Requires-Dist: jsonpath ~=0.82
Requires-Dist: jsonschema ==4.21.1
Requires-Dist: jsonschema-specifications ==2023.12.1
Requires-Dist: jupyter-client ==8.6.1
Requires-Dist: jupyter-core ==5.7.2
Requires-Dist: jupyterlab-pygments ==0.3.0
Requires-Dist: MarkupSafe ==2.1.5
Requires-Dist: matplotlib-inline ==0.1.6
Requires-Dist: mistune ==3.0.2
Requires-Dist: mypy-extensions ==1.0.0
Requires-Dist: nbclient ==0.10.0
Requires-Dist: nbconvert ==7.16.2
Requires-Dist: nbformat ==5.10.2
Requires-Dist: packaging ==23.1
Requires-Dist: pandocfilters ==1.5.1
Requires-Dist: parso ==0.8.3
Requires-Dist: pathspec ==0.12.1
Requires-Dist: pickleshare ==0.7.5
Requires-Dist: pipreqs ==0.5.0
Requires-Dist: platformdirs ==4.2.0
Requires-Dist: pluggy ==1.4.0
Requires-Dist: prompt-toolkit ==3.0.43
Requires-Dist: pure-eval ==0.2.2
Requires-Dist: pyee ==11.1.0
Requires-Dist: Pygments ==2.17.2
Requires-Dist: PyMySQL ~=1.0.2
Requires-Dist: pytest ~=7.2.0
Requires-Dist: python-dateutil ==2.8.2
Requires-Dist: PyYAML ~=6.0
Requires-Dist: pyzmq ==25.1.2
Requires-Dist: referencing ==0.33.0
Requires-Dist: requests ~=2.28.1
Requires-Dist: requests-toolbelt ==1.0.0
Requires-Dist: rpds-py ==0.18.0
Requires-Dist: six ==1.16.0
Requires-Dist: soupsieve ==2.5
Requires-Dist: stack-data ==0.6.3
Requires-Dist: tinycss2 ==1.2.1
Requires-Dist: tornado ==6.4
Requires-Dist: traitlets ==5.14.2
Requires-Dist: typing-extensions ==4.10.0
Requires-Dist: urllib3 ==1.26.18
Requires-Dist: wcwidth ==0.2.13
Requires-Dist: webencodings ==0.5.1
Requires-Dist: yarg ==0.1.9
Requires-Dist: jsonpath-ng ==1.6.1
